si/__init__.py
si/amp.py
si/no_op_amp.py
si/session.py
si/smart_conn.py
client_scaledinference-1.0.1.dist-info/LICENSE
client_scaledinference-1.0.1.dist-info/METADATA
client_scaledinference-1.0.1.dist-info/WHEEL
client_scaledinference-1.0.1.dist-info/top_level.txt
client_scaledinference-1.0.1.dist-info/RECORD
